README.md
pyproject.toml
toxicmaster/__init__.py
toxicmaster/aws.py
toxicmaster/build.py
toxicmaster/client.py
toxicmaster/cmds.py
toxicmaster/consumers.py
toxicmaster/document.py
toxicmaster/exceptions.py
toxicmaster/hole.py
toxicmaster/repository.py
toxicmaster/scheduler.py
toxicmaster/signals.py
toxicmaster/slave.py
toxicmaster/users.py
toxicmaster/utils.py
toxicmaster/waterfall.py
toxicmaster.egg-info/PKG-INFO
toxicmaster.egg-info/SOURCES.txt
toxicmaster.egg-info/dependency_links.txt
toxicmaster.egg-info/entry_points.txt
toxicmaster.egg-info/requires.txt
toxicmaster.egg-info/top_level.txt